{
	"name": "fireWorks",
	"plugin-id": "Sprite",
	"sid": 949733503345144,
	"isGlobal": false,
	"instanceVariables": [],
	"behaviorTypes": [],
	"effectTypes": [],
	"animations": {
		"items": [
			{
				"frames": [
					{
						"width": 1280,
						"height": 720,
						"originX": 0.5,
						"originY": 0.5,
						"originalSource": "",
						"exportFormat": "lossless",
						"exportQuality": 0.8,
						"imageSpriteId": 2009092,
						"useCollisionPoly": true,
						"duration": 1,
						"tag": ""
					},
					{
						"width": 10,
						"height": 10,
						"originX": 0.5,
						"originY": 0.5,
						"originalSource": "",
						"exportFormat": "lossless",
						"exportQuality": 0.8,
						"imageSpriteId": 4697665,
						"useCollisionPoly": true,
						"duration": 1,
						"tag": ""
					},
					{
						"width": 10,
						"height": 10,
						"originX": 0.5,
						"originY": 0.5,
						"originalSource": "",
						"exportFormat": "lossless",
						"exportQuality": 0.8,
						"imageSpriteId": 3661809,
						"useCollisionPoly": true,
						"duration": 1,
						"tag": ""
					},
					{
						"width": 58,
						"height": 58,
						"originX": 0.5,
						"originY": 0.5,
						"originalSource": "",
						"exportFormat": "lossless",
						"exportQuality": 0.8,
						"imageSpriteId": 2058981,
						"useCollisionPoly": true,
						"duration": 1,
						"tag": ""
					},
					{
						"width": 120,
						"height": 120,
						"originX": 0.5,
						"originY": 0.5,
						"originalSource": "",
						"exportFormat": "lossless",
						"exportQuality": 0.8,
						"imageSpriteId": 8265700,
						"useCollisionPoly": true,
						"duration": 1,
						"tag": ""
					},
					{
						"width": 246,
						"height": 246,
						"originX": 0.5,
						"originY": 0.5,
						"originalSource": "",
						"exportFormat": "lossless",
						"exportQuality": 0.8,
						"imageSpriteId": 7337805,
						"useCollisionPoly": true,
						"duration": 1,
						"tag": ""
					},
					{
						"width": 408,
						"height": 408,
						"originX": 0.5,
						"originY": 0.5,
						"originalSource": "",
						"exportFormat": "lossless",
						"exportQuality": 0.8,
						"imageSpriteId": 5316427,
						"useCollisionPoly": true,
						"duration": 1,
						"tag": ""
					},
					{
						"width": 498,
						"height": 498,
						"originX": 0.5,
						"originY": 0.5,
						"originalSource": "",
						"exportFormat": "lossless",
						"exportQuality": 0.8,
						"imageSpriteId": 9545814,
						"useCollisionPoly": true,
						"duration": 1,
						"tag": ""
					},
					{
						"width": 510,
						"height": 510,
						"originX": 0.5,
						"originY": 0.5,
						"originalSource": "",
						"exportFormat": "lossless",
						"exportQuality": 0.8,
						"imageSpriteId": 7948724,
						"useCollisionPoly": true,
						"duration": 1,
						"tag": ""
					},
					{
						"width": 552,
						"height": 552,
						"originX": 0.5,
						"originY": 0.5,
						"originalSource": "",
						"exportFormat": "lossless",
						"exportQuality": 0.8,
						"imageSpriteId": 8959852,
						"useCollisionPoly": true,
						"duration": 1,
						"tag": ""
					},
					{
						"width": 552,
						"height": 552,
						"originX": 0.5,
						"originY": 0.5,
						"originalSource": "",
						"exportFormat": "lossless",
						"exportQuality": 0.8,
						"imageSpriteId": 9155825,
						"useCollisionPoly": true,
						"duration": 1,
						"tag": ""
					},
					{
						"width": 571,
						"height": 570,
						"originX": 0.4991243432574431,
						"originY": 0.5,
						"originalSource": "",
						"exportFormat": "lossless",
						"exportQuality": 0.8,
						"imageSpriteId": 3007107,
						"useCollisionPoly": true,
						"duration": 1,
						"tag": ""
					},
					{
						"width": 578,
						"height": 578,
						"originX": 0.5,
						"originY": 0.5,
						"originalSource": "",
						"exportFormat": "lossless",
						"exportQuality": 0.8,
						"imageSpriteId": 2218077,
						"useCollisionPoly": true,
						"duration": 1,
						"tag": ""
					},
					{
						"width": 362,
						"height": 362,
						"originX": 0.5,
						"originY": 0.5,
						"originalSource": "",
						"exportFormat": "lossless",
						"exportQuality": 0.8,
						"imageSpriteId": 3447132,
						"useCollisionPoly": true,
						"duration": 1,
						"tag": ""
					},
					{
						"width": 1280,
						"height": 720,
						"originX": 0.5,
						"originY": 0.5,
						"originalSource": "",
						"exportFormat": "lossless",
						"exportQuality": 0.8,
						"imageSpriteId": 5088517,
						"useCollisionPoly": true,
						"duration": 1,
						"tag": ""
					},
					{
						"width": 10,
						"height": 10,
						"originX": 0.5,
						"originY": 0.5,
						"originalSource": "",
						"exportFormat": "lossless",
						"exportQuality": 0.8,
						"imageSpriteId": 5478825,
						"useCollisionPoly": true,
						"duration": 1,
						"tag": ""
					},
					{
						"width": 10,
						"height": 10,
						"originX": 0.5,
						"originY": 0.5,
						"originalSource": "",
						"exportFormat": "lossless",
						"exportQuality": 0.8,
						"imageSpriteId": 4273304,
						"useCollisionPoly": true,
						"duration": 1,
						"tag": ""
					},
					{
						"width": 58,
						"height": 58,
						"originX": 0.5,
						"originY": 0.5,
						"originalSource": "",
						"exportFormat": "lossless",
						"exportQuality": 0.8,
						"imageSpriteId": 9060125,
						"useCollisionPoly": true,
						"duration": 1,
						"tag": ""
					},
					{
						"width": 120,
						"height": 120,
						"originX": 0.5,
						"originY": 0.5,
						"originalSource": "",
						"exportFormat": "lossless",
						"exportQuality": 0.8,
						"imageSpriteId": 9968139,
						"useCollisionPoly": true,
						"duration": 1,
						"tag": ""
					},
					{
						"width": 246,
						"height": 246,
						"originX": 0.5,
						"originY": 0.5,
						"originalSource": "",
						"exportFormat": "lossless",
						"exportQuality": 0.8,
						"imageSpriteId": 6021389,
						"useCollisionPoly": true,
						"duration": 1,
						"tag": ""
					},
					{
						"width": 408,
						"height": 408,
						"originX": 0.5,
						"originY": 0.5,
						"originalSource": "",
						"exportFormat": "lossless",
						"exportQuality": 0.8,
						"imageSpriteId": 8510651,
						"useCollisionPoly": true,
						"duration": 1,
						"tag": ""
					},
					{
						"width": 498,
						"height": 498,
						"originX": 0.5,
						"originY": 0.5,
						"originalSource": "",
						"exportFormat": "lossless",
						"exportQuality": 0.8,
						"imageSpriteId": 7754982,
						"useCollisionPoly": true,
						"duration": 1,
						"tag": ""
					},
					{
						"width": 510,
						"height": 510,
						"originX": 0.5,
						"originY": 0.5,
						"originalSource": "",
						"exportFormat": "lossless",
						"exportQuality": 0.8,
						"imageSpriteId": 4812539,
						"useCollisionPoly": true,
						"duration": 1,
						"tag": ""
					},
					{
						"width": 552,
						"height": 552,
						"originX": 0.5,
						"originY": 0.5,
						"originalSource": "",
						"exportFormat": "lossless",
						"exportQuality": 0.8,
						"imageSpriteId": 8576740,
						"useCollisionPoly": true,
						"duration": 1,
						"tag": ""
					},
					{
						"width": 552,
						"height": 552,
						"originX": 0.5,
						"originY": 0.5,
						"originalSource": "",
						"exportFormat": "lossless",
						"exportQuality": 0.8,
						"imageSpriteId": 4325749,
						"useCollisionPoly": true,
						"duration": 1,
						"tag": ""
					},
					{
						"width": 571,
						"height": 570,
						"originX": 0.4991243432574431,
						"originY": 0.5,
						"originalSource": "",
						"exportFormat": "lossless",
						"exportQuality": 0.8,
						"imageSpriteId": 8808379,
						"useCollisionPoly": true,
						"duration": 1,
						"tag": ""
					},
					{
						"width": 578,
						"height": 578,
						"originX": 0.5,
						"originY": 0.5,
						"originalSource": "",
						"exportFormat": "lossless",
						"exportQuality": 0.8,
						"imageSpriteId": 9601598,
						"useCollisionPoly": true,
						"duration": 1,
						"tag": ""
					},
					{
						"width": 362,
						"height": 362,
						"originX": 0.5,
						"originY": 0.5,
						"originalSource": "",
						"exportFormat": "lossless",
						"exportQuality": 0.8,
						"imageSpriteId": 3256581,
						"useCollisionPoly": true,
						"duration": 1,
						"tag": ""
					},
					{
						"width": 1280,
						"height": 720,
						"originX": 0.5,
						"originY": 0.5,
						"originalSource": "",
						"exportFormat": "lossless",
						"exportQuality": 0.8,
						"imageSpriteId": 4094994,
						"useCollisionPoly": true,
						"duration": 1,
						"tag": ""
					},
					{
						"width": 10,
						"height": 10,
						"originX": 0.5,
						"originY": 0.5,
						"originalSource": "",
						"exportFormat": "lossless",
						"exportQuality": 0.8,
						"imageSpriteId": 1395480,
						"useCollisionPoly": true,
						"duration": 1,
						"tag": ""
					},
					{
						"width": 10,
						"height": 10,
						"originX": 0.5,
						"originY": 0.5,
						"originalSource": "",
						"exportFormat": "lossless",
						"exportQuality": 0.8,
						"imageSpriteId": 2525856,
						"useCollisionPoly": true,
						"duration": 1,
						"tag": ""
					},
					{
						"width": 58,
						"height": 58,
						"originX": 0.5,
						"originY": 0.5,
						"originalSource": "",
						"exportFormat": "lossless",
						"exportQuality": 0.8,
						"imageSpriteId": 8361395,
						"useCollisionPoly": true,
						"duration": 1,
						"tag": ""
					},
					{
						"width": 120,
						"height": 120,
						"originX": 0.5,
						"originY": 0.5,
						"originalSource": "",
						"exportFormat": "lossless",
						"exportQuality": 0.8,
						"imageSpriteId": 6509974,
						"useCollisionPoly": true,
						"duration": 1,
						"tag": ""
					},
					{
						"width": 246,
						"height": 246,
						"originX": 0.5,
						"originY": 0.5,
						"originalSource": "",
						"exportFormat": "lossless",
						"exportQuality": 0.8,
						"imageSpriteId": 1703256,
						"useCollisionPoly": true,
						"duration": 1,
						"tag": ""
					},
					{
						"width": 408,
						"height": 408,
						"originX": 0.5,
						"originY": 0.5,
						"originalSource": "",
						"exportFormat": "lossless",
						"exportQuality": 0.8,
						"imageSpriteId": 7827966,
						"useCollisionPoly": true,
						"duration": 1,
						"tag": ""
					},
					{
						"width": 498,
						"height": 498,
						"originX": 0.5,
						"originY": 0.5,
						"originalSource": "",
						"exportFormat": "lossless",
						"exportQuality": 0.8,
						"imageSpriteId": 4818622,
						"useCollisionPoly": true,
						"duration": 1,
						"tag": ""
					},
					{
						"width": 510,
						"height": 510,
						"originX": 0.5,
						"originY": 0.5,
						"originalSource": "",
						"exportFormat": "lossless",
						"exportQuality": 0.8,
						"imageSpriteId": 6027021,
						"useCollisionPoly": true,
						"duration": 1,
						"tag": ""
					},
					{
						"width": 552,
						"height": 552,
						"originX": 0.5,
						"originY": 0.5,
						"originalSource": "",
						"exportFormat": "lossless",
						"exportQuality": 0.8,
						"imageSpriteId": 6963750,
						"useCollisionPoly": true,
						"duration": 1,
						"tag": ""
					},
					{
						"width": 552,
						"height": 552,
						"originX": 0.5,
						"originY": 0.5,
						"originalSource": "",
						"exportFormat": "lossless",
						"exportQuality": 0.8,
						"imageSpriteId": 9141138,
						"useCollisionPoly": true,
						"duration": 1,
						"tag": ""
					},
					{
						"width": 571,
						"height": 570,
						"originX": 0.4991243432574431,
						"originY": 0.5,
						"originalSource": "",
						"exportFormat": "lossless",
						"exportQuality": 0.8,
						"imageSpriteId": 2436770,
						"useCollisionPoly": true,
						"duration": 1,
						"tag": ""
					},
					{
						"width": 578,
						"height": 578,
						"originX": 0.5,
						"originY": 0.5,
						"originalSource": "",
						"exportFormat": "lossless",
						"exportQuality": 0.8,
						"imageSpriteId": 906382,
						"useCollisionPoly": true,
						"duration": 1,
						"tag": ""
					},
					{
						"width": 362,
						"height": 362,
						"originX": 0.5,
						"originY": 0.5,
						"originalSource": "",
						"exportFormat": "lossless",
						"exportQuality": 0.8,
						"imageSpriteId": 3698171,
						"useCollisionPoly": true,
						"duration": 1,
						"tag": ""
					},
					{
						"width": 1280,
						"height": 720,
						"originX": 0.5,
						"originY": 0.5,
						"originalSource": "",
						"exportFormat": "lossless",
						"exportQuality": 0.8,
						"imageSpriteId": 8507434,
						"useCollisionPoly": true,
						"duration": 1,
						"tag": ""
					}
				],
				"sid": 711610156292525,
				"name": "Default",
				"isLooping": true,
				"isPingPong": false,
				"repeatCount": 1,
				"repeatTo": 0,
				"speed": 30
			}
		],
		"subfolders": []
	}
}